langcrawler/__init__.py
langcrawler/main.py
langcrawler/cmd/__init__.py
langcrawler/cmd/argument.py
langcrawler/cmd/banner.py
langcrawler/cmd/version.py
langcrawler/config/__init__.py
langcrawler/config/config.py
langcrawler/fetcher/__init__.py
langcrawler/fetcher/fetcher.py
langcrawler/fetcher/gerrit.py
langcrawler/fetcher/github.py
langcrawler/fetcher/gitlab.py
langcrawler/logger/__init__.py
langcrawler/logger/logger.py
langcrawler/queue/__init__.py
langcrawler/queue/queue.py
langcrawler/request/__init__.py
langcrawler/request/request.py
langcrawler/scheduler/__init__.py
langcrawler/scheduler/scheduler.py
langcrawler/schema/__init__.py
langcrawler/schema/schema.py
langcrawler/storage/__init__.py
langcrawler/storage/storage.py
langcrawler-0.0.4.dist-info/LICENSE
langcrawler-0.0.4.dist-info/METADATA
langcrawler-0.0.4.dist-info/WHEEL
langcrawler-0.0.4.dist-info/entry_points.txt
langcrawler-0.0.4.dist-info/top_level.txt
langcrawler-0.0.4.dist-info/RECORD
