Metadata-Version: 2.1
Name: langcrawler
Version: 0.0.4
Summary: Language Crawler
Home-page: https://github.com/craftslab/langcrawler
Author: Jia Jia
Author-email: angersax@sina.com
License: Apache-2.0
Download-URL: https://github.com/craftslab/langcrawler/archive/v0.0.4.tar.gz
Keywords: lang,language,crawler,spider
Platform: UNKNOWN
Classifier: Programming Language :: Python :: 3
Classifier: License :: OSI Approved :: Apache Software License
Classifier: Operating System :: OS Independent
Requires-Dist: black
Requires-Dist: colorama
Requires-Dist: coverage
Requires-Dist: coveralls
Requires-Dist: hypothesis
Requires-Dist: flake8
Requires-Dist: mypy
Requires-Dist: pre-commit
Requires-Dist: psycopg2-binary
Requires-Dist: pytest
Requires-Dist: redis
Requires-Dist: requests
Requires-Dist: setuptools
Requires-Dist: twine
Requires-Dist: wheel
